AUTHORS
LICENSE
MANIFEST.in
README.rst
RELEASE-VERSION
setup.py
docs/overview.rst
docs/steelhead.rst
docs/toc.rst
docs/tutorial.rst
examples/steelhead_api.py
examples/steelhead_cli.py
gitpy_versioning/__init__.py
steelscript/__init__.py
steelscript.steelhead.egg-info/PKG-INFO
steelscript.steelhead.egg-info/SOURCES.txt
steelscript.steelhead.egg-info/dependency_links.txt
steelscript.steelhead.egg-info/entry_points.txt
steelscript.steelhead.egg-info/namespace_packages.txt
steelscript.steelhead.egg-info/requires.txt
steelscript.steelhead.egg-info/top_level.txt
steelscript/steelhead/__init__.py
steelscript/steelhead/appfwk/__init__.py
steelscript/steelhead/appfwk/plugin.py
steelscript/steelhead/appfwk/datasources/__init__.py
steelscript/steelhead/appfwk/datasources/steelhead.py
steelscript/steelhead/appfwk/devices/__init__.py
steelscript/steelhead/appfwk/devices/steelhead.py
steelscript/steelhead/appfwk/reports/__init__.py
steelscript/steelhead/appfwk/reports/steelhead.py
steelscript/steelhead/appfwk/reports/steelhead_batch.py
steelscript/steelhead/core/__init__.py
steelscript/steelhead/core/steelhead.py
steelscript/steelhead/features/__init__.py
steelscript/steelhead/features/common/__init__.py
steelscript/steelhead/features/common/v8_5/__init__.py
steelscript/steelhead/features/common/v8_5/action.py
steelscript/steelhead/features/common/v8_5/model.py
steelscript/steelhead/features/flows/__init__.py
steelscript/steelhead/features/flows/v8_5/__init__.py
steelscript/steelhead/features/flows/v8_5/action.py
steelscript/steelhead/features/flows/v8_5/model.py
steelscript/steelhead/features/networking/__init__.py
steelscript/steelhead/features/networking/v8_5/__init__.py
steelscript/steelhead/features/networking/v8_5/model.py
steelscript/steelhead/features/stats/__init__.py
steelscript/steelhead/features/stats/v8_5/__init__.py
steelscript/steelhead/features/stats/v8_5/model.py